terminalgpt/__init__.py
terminalgpt/chat.py
terminalgpt/config.py
terminalgpt/conversations.py
terminalgpt/encryption.py
terminalgpt/main.py
terminalgpt/printer.py
tests/__init__.py
TerminalGPT_main-0.2.dist-info/LICENSE
TerminalGPT_main-0.2.dist-info/METADATA
TerminalGPT_main-0.2.dist-info/WHEEL
TerminalGPT_main-0.2.dist-info/entry_points.txt
TerminalGPT_main-0.2.dist-info/top_level.txt
TerminalGPT_main-0.2.dist-info/RECORD
